Workbook

Sheet 宅建業法
A1: № | B1: 問題 | C1: 解答 | D1: 設問画像 | E1: 解答画像 | F1: 解説 | G1: 科目名 | H1: タグ（論点） | I1: キーワード
A2: Q001 | B2: =IF($A2="","",VLOOKUP($A2,データ宅建業法!$A$2:$E$500,3,FALSE)) -> 準工業地域内の土地は建築資材置場として利用されていても宅地である | C2: =IF($A2="","",VLOOKUP($A2,データ宅建業法!$A$2:$E$500,4,FALSE)) -> ○ | F2: =IF($A2="","",VLOOKUP($A2,データ宅建業法!$A$2:$E$500,5,FALSE)) -> 用途地域内の土地は道路・公園など公共施設を除き宅地となる | H2: =IF($A2="","",VLOOKUP($A2,データ宅建業法!$A$2:$E$500,5,FALSE)) -> 用途地域内の土地は道路・公園など公共施設を除き宅地となる
A3: Q002 | B3: =IF($A3="","",VLOOKUP($A3,データ宅建業法!$A$2:$E$500,3,FALSE)) -> 用途地域内の土地は建物が建っていなくても宅地である | C3: =IF($A3="","",VLOOKUP($A3,データ宅建業法!$A$2:$E$500,4,FALSE)) -> ○ | F3: =IF($A3="","",VLOOKUP($A3,データ宅建業法!$A$2:$E$500,5,FALSE)) -> 用途地域内の土地は現況に関係なく宅地となる | H3: =IF($A3="","",VLOOKUP($A3,データ宅建業法!$A$2:$E$500,5,FALSE)) -> 用途地域内の土地は現況に関係なく宅地となる
A4: Q003 | B4: =IF($A4="","",VLOOKUP($A4,データ宅建業法!$A$2:$E$500,3,FALSE)) -> 用途地域外の土地は宅地には該当しない | C4: =IF($A4="","",VLOOKUP($A4,データ宅建業法!$A$2:$E$500,4,FALSE)) -> × | F4: =IF($A4="","",VLOOKUP($A4,データ宅建業法!$A$2:$E$500,5,FALSE)) -> 用途地域外でも建物敷地として使用される土地は宅地 | H4: =IF($A4="","",VLOOKUP($A4,データ宅建業法!$A$2:$E$500,5,FALSE)) -> 用途地域外でも建物敷地として使用される土地は宅地
A5: Q004 | B5: =IF($A5="","",VLOOKUP($A5,データ宅建業法!$A$2:$E$500,3,FALSE)) -> 道路は宅地に該当する | C5: =IF($A5="","",VLOOKUP($A5,データ宅建業法!$A$2:$E$500,4,FALSE)) -> × | F5: =IF($A5="","",VLOOKUP($A5,データ宅建業法!$A$2:$E$500,5,FALSE)) -> 道路・河川・公園など公共施設の用地は宅地ではない | H5: =IF($A5="","",VLOOKUP($A5,データ宅建業法!$A$2:$E$500,5,FALSE)) -> 道路・河川・公園など公共施設の用地は宅地ではない
A6: Q005 | B6: =IF($A6="","",VLOOKUP($A6,データ宅建業法!$A$2:$E$500,3,FALSE)) -> 駐車場として利用されている土地は宅地である | C6: =IF($A6="","",VLOOKUP($A6,データ宅建業法!$A$2:$E$500,4,FALSE)) -> ○ | F6: =IF($A6="","",VLOOKUP($A6,データ宅建業法!$A$2:$E$500,5,FALSE)) -> 建物敷地以外でも宅地に該当する場合がある | H6: =IF($A6="","",VLOOKUP($A6,データ宅建業法!$A$2:$E$500,5,FALSE)) -> 建物敷地以外でも宅地に該当する場合がある
A7: Q006 | B7: =IF($A7="","",VLOOKUP($A7,データ宅建業法!$A$2:$E$500,3,FALSE)) -> 宅地の売買を1回だけ行う場合宅建業に該当する | C7: =IF($A7="","",VLOOKUP($A7,データ宅建業法!$A$2:$E$500,4,FALSE)) -> × | F7: =IF($A7="","",VLOOKUP($A7,データ宅建業法!$A$2:$E$500,5,FALSE)) -> 宅建業は反復継続が必要 | H7: =IF($A7="","",VLOOKUP($A7,データ宅建業法!$A$2:$E$500,5,FALSE)) -> 宅建業は反復継続が必要
A8: Q007 | B8: =IF($A8="","",VLOOKUP($A8,データ宅建業法!$A$2:$E$500,3,FALSE)) -> 宅地の売買を反復継続して行う場合宅建業となる | C8: =IF($A8="","",VLOOKUP($A8,データ宅建業法!$A$2:$E$500,4,FALSE)) -> ○ | F8: =IF($A8="","",VLOOKUP($A8,データ宅建業法!$A$2:$E$500,5,FALSE)) -> 反復継続して売買する場合は宅建業 | H8: =IF($A8="","",VLOOKUP($A8,データ宅建業法!$A$2:$E$500,5,FALSE)) -> 反復継続して売買する場合は宅建業
A9: Q008 | B9: =IF($A9="","",VLOOKUP($A9,データ宅建業法!$A$2:$E$500,3,FALSE)) -> 建物の賃貸の媒介は宅建業である | C9: =IF($A9="","",VLOOKUP($A9,データ宅建業法!$A$2:$E$500,4,FALSE)) -> ○ | F9: =IF($A9="","",VLOOKUP($A9,データ宅建業法!$A$2:$E$500,5,FALSE)) -> 賃貸の代理・媒介は宅建業 | H9: =IF($A9="","",VLOOKUP($A9,データ宅建業法!$A$2:$E$500,5,FALSE)) -> 賃貸の代理・媒介は宅建業
A10: Q009 | B10: =IF($A10="","",VLOOKUP($A10,データ宅建業法!$A$2:$E$500,3,FALSE)) -> 自ら貸主として賃貸する行為は宅建業である | C10: =IF($A10="","",VLOOKUP($A10,データ宅建業法!$A$2:$E$500,4,FALSE)) -> × | F10: =IF($A10="","",VLOOKUP($A10,データ宅建業法!$A$2:$E$500,5,FALSE)) -> 貸借は宅建業に含まれない | H10: =IF($A10="","",VLOOKUP($A10,データ宅建業法!$A$2:$E$500,5,FALSE)) -> 貸借は宅建業に含まれない
A11: Q010 | B11: =IF($A11="","",VLOOKUP($A11,データ宅建業法!$A$2:$E$500,3,FALSE)) -> 宅地売買の媒介は宅建業に該当する | C11: =IF($A11="","",VLOOKUP($A11,データ宅建業法!$A$2:$E$500,4,FALSE)) -> ○ | F11: =IF($A11="","",VLOOKUP($A11,データ宅建業法!$A$2:$E$500,5,FALSE)) -> 売買の媒介は宅建業 | H11: =IF($A11="","",VLOOKUP($A11,データ宅建業法!$A$2:$E$500,5,FALSE)) -> 売買の媒介は宅建業
A12: Q011 | B12: =IF($A12="","",VLOOKUP($A12,データ宅建業法!$A$2:$E$500,3,FALSE)) -> 宅建業免許の有効期間は5年である | C12: =IF($A12="","",VLOOKUP($A12,データ宅建業法!$A$2:$E$500,4,FALSE)) -> ○ | F12: =IF($A12="","",VLOOKUP($A12,データ宅建業法!$A$2:$E$500,5,FALSE)) -> 宅建業免許は5年ごと更新 | H12: =IF($A12="","",VLOOKUP($A12,データ宅建業法!$A$2:$E$500,5,FALSE)) -> 宅建業免許は5年ごと更新
A13: Q012 | B13: =IF($A13="","",VLOOKUP($A13,データ宅建業法!$A$2:$E$500,3,FALSE)) -> 免許更新は満了後でも可能である | C13: =IF($A13="","",VLOOKUP($A13,データ宅建業法!$A$2:$E$500,4,FALSE)) -> × | F13: =IF($A13="","",VLOOKUP($A13,データ宅建業法!$A$2:$E$500,5,FALSE)) -> 満了前に申請必要 | H13: =IF($A13="","",VLOOKUP($A13,データ宅建業法!$A$2:$E$500,5,FALSE)) -> 満了前に申請必要
... A126: Q125 | B126: =IF($A126="","",VLOOKUP($A126,データ宅建業法!$A$2:$E$500,3,FALSE)) -> 名義貸しは禁止されている | C126: =IF($A126="","",VLOOKUP($A126,データ宅建業法!$A$2:$E$500,4,FALSE)) -> ○ | F126: =IF($A126="","",VLOOKUP($A126,データ宅建業法!$A$2:$E$500,5,FALSE)) -> 宅建業者の名義貸しは禁止 | H126: =IF($A126="","",VLOOKUP($A126,データ宅建業法!$A$2:$E$500,5,FALSE)) -> 宅建業者の名義貸しは禁止
A127: ="Q"&ROW()-1 -> Q126 | B127: 宅建士の法的業務 | C127: 重要事項の説明、重要事項の説明書に記名、契約書に記名

Sheet 民法
A1: № | B1: 問題 | C1: 解答 | D1: 設問画像 | E1: 解答画像 | F1: 解説 | G1: 科目名 | H1: タグ（論点） | I1: キーワード
A2: =IF(B2="","",ROW()-1) -> 1 | B2: 作成中 | C2: 作成中
A3: =IF(B3="","",ROW()-1) | G3: =IF(B3="","",MID(CELL("filename",A2),FIND("]",CELL("filename",A2))+1,31))
A4: =IF(B4="","",ROW()-1) | G4: =IF(B4="","",MID(CELL("filename",A3),FIND("]",CELL("filename",A3))+1,31))
A5: =IF(B5="","",ROW()-1) | G5: =IF(B5="","",MID(CELL("filename",A4),FIND("]",CELL("filename",A4))+1,31))
A6: =IF(B6="","",ROW()-1) | G6: =IF(B6="","",MID(CELL("filename",A5),FIND("]",CELL("filename",A5))+1,31))
A7: =IF(B7="","",ROW()-1) | G7: =IF(B7="","",MID(CELL("filename",A6),FIND("]",CELL("filename",A6))+1,31))
A8: =IF(B8="","",ROW()-1) | G8: =IF(B8="","",MID(CELL("filename",A7),FIND("]",CELL("filename",A7))+1,31))
A9: =IF(B9="","",ROW()-1) | G9: =IF(B9="","",MID(CELL("filename",A8),FIND("]",CELL("filename",A8))+1,31))
A10: =IF(B10="","",ROW()-1) | G10: =IF(B10="","",MID(CELL("filename",A9),FIND("]",CELL("filename",A9))+1,31))
A11: =IF(B11="","",ROW()-1) | G11: =IF(B11="","",MID(CELL("filename",A10),FIND("]",CELL("filename",A10))+1,31))
A12: =IF(B12="","",ROW()-1) | G12: =IF(B12="","",MID(CELL("filename",A11),FIND("]",CELL("filename",A11))+1,31))
A13: =IF(B13="","",ROW()-1) | G13: =IF(B13="","",MID(CELL("filename",A12),FIND("]",CELL("filename",A12))+1,31))
A14: =IF(B14="","",ROW()-1) | G14: =IF(B14="","",MID(CELL("filename",A13),FIND("]",CELL("filename",A13))+1,31))
... A100: =IF(B100="","",ROW()-1) | G100: =IF(B100="","",MID(CELL("filename",A99),FIND("]",CELL("filename",A99))+1,31))

Sheet 法令上の制限
A1: № | B1: 問題 | C1: 解答 | D1: 設問画像 | E1: 解答画像 | F1: 解説 | G1: 科目名 | H1: タグ（論点） | I1: キーワード
A2: =IF(B2="","",ROW()-1) -> 1 | B2: 作成中 | C2: 作成中
A3: =IF(B3="","",ROW()-1) | G3: =IF(B3="","",MID(CELL("filename",A2),FIND("]",CELL("filename",A2))+1,31))
A4: =IF(B4="","",ROW()-1) | G4: =IF(B4="","",MID(CELL("filename",A3),FIND("]",CELL("filename",A3))+1,31))
A5: =IF(B5="","",ROW()-1) | G5: =IF(B5="","",MID(CELL("filename",A4),FIND("]",CELL("filename",A4))+1,31))
A6: =IF(B6="","",ROW()-1) | G6: =IF(B6="","",MID(CELL("filename",A5),FIND("]",CELL("filename",A5))+1,31))
A7: =IF(B7="","",ROW()-1) | G7: =IF(B7="","",MID(CELL("filename",A6),FIND("]",CELL("filename",A6))+1,31))
A8: =IF(B8="","",ROW()-1) | G8: =IF(B8="","",MID(CELL("filename",A7),FIND("]",CELL("filename",A7))+1,31))
A9: =IF(B9="","",ROW()-1) | G9: =IF(B9="","",MID(CELL("filename",A8),FIND("]",CELL("filename",A8))+1,31))
A10: =IF(B10="","",ROW()-1) | G10: =IF(B10="","",MID(CELL("filename",A9),FIND("]",CELL("filename",A9))+1,31))
A11: =IF(B11="","",ROW()-1) | G11: =IF(B11="","",MID(CELL("filename",A10),FIND("]",CELL("filename",A10))+1,31))
A12: =IF(B12="","",ROW()-1) | G12: =IF(B12="","",MID(CELL("filename",A11),FIND("]",CELL("filename",A11))+1,31))
A13: =IF(B13="","",ROW()-1) | G13: =IF(B13="","",MID(CELL("filename",A12),FIND("]",CELL("filename",A12))+1,31))
A14: =IF(B14="","",ROW()-1) | G14: =IF(B14="","",MID(CELL("filename",A13),FIND("]",CELL("filename",A13))+1,31))
... A100: =IF(B100="","",ROW()-1) | G100: =IF(B100="","",MID(CELL("filename",A99),FIND("]",CELL("filename",A99))+1,31))

Sheet その他関連知識
A1: № | B1: 問題 | C1: 解答 | D1: 設問画像 | E1: 解答画像 | F1: 解説 | G1: 科目名 | H1: タグ（論点） | I1: キーワード
A2: =IF(B2="","",ROW()-1) -> 1 | B2: 作成中 | C2: 作成中
A3: =IF(B3="","",ROW()-1) | G3: =IF(B3="","",MID(CELL("filename",A2),FIND("]",CELL("filename",A2))+1,31))
A4: =IF(B4="","",ROW()-1) | G4: =IF(B4="","",MID(CELL("filename",A3),FIND("]",CELL("filename",A3))+1,31))
A5: =IF(B5="","",ROW()-1) | G5: =IF(B5="","",MID(CELL("filename",A4),FIND("]",CELL("filename",A4))+1,31))
A6: =IF(B6="","",ROW()-1) | G6: =IF(B6="","",MID(CELL("filename",A5),FIND("]",CELL("filename",A5))+1,31))
A7: =IF(B7="","",ROW()-1) | G7: =IF(B7="","",MID(CELL("filename",A6),FIND("]",CELL("filename",A6))+1,31))
A8: =IF(B8="","",ROW()-1) | G8: =IF(B8="","",MID(CELL("filename",A7),FIND("]",CELL("filename",A7))+1,31))
A9: =IF(B9="","",ROW()-1) | G9: =IF(B9="","",MID(CELL("filename",A8),FIND("]",CELL("filename",A8))+1,31))
A10: =IF(B10="","",ROW()-1) | G10: =IF(B10="","",MID(CELL("filename",A9),FIND("]",CELL("filename",A9))+1,31))
A11: =IF(B11="","",ROW()-1) | G11: =IF(B11="","",MID(CELL("filename",A10),FIND("]",CELL("filename",A10))+1,31))
A12: =IF(B12="","",ROW()-1) | G12: =IF(B12="","",MID(CELL("filename",A11),FIND("]",CELL("filename",A11))+1,31))
A13: =IF(B13="","",ROW()-1) | G13: =IF(B13="","",MID(CELL("filename",A12),FIND("]",CELL("filename",A12))+1,31))
A14: =IF(B14="","",ROW()-1) | G14: =IF(B14="","",MID(CELL("filename",A13),FIND("]",CELL("filename",A13))+1,31))
... A100: =IF(B100="","",ROW()-1) | G100: =IF(B100="","",MID(CELL("filename",A99),FIND("]",CELL("filename",A99))+1,31))

Sheet データ宅建業法
A1: カードNo | B1: 論点 | C1: 問題 | D1: 解答 | E1: 解説
A2: Q001 | B2: 宅地の定義 | C2: 準工業地域内の土地は建築資材置場として利用されていても宅地である | D2: ○ | E2: 用途地域内の土地は道路・公園など公共施設を除き宅地となる
A3: Q002 | B3: 宅地の定義 | C3: 用途地域内の土地は建物が建っていなくても宅地である | D3: ○ | E3: 用途地域内の土地は現況に関係なく宅地となる
A4: Q003 | B4: 宅地の定義 | C4: 用途地域外の土地は宅地には該当しない | D4: × | E4: 用途地域外でも建物敷地として使用される土地は宅地
A5: Q004 | B5: 宅地の定義 | C5: 道路は宅地に該当する | D5: × | E5: 道路・河川・公園など公共施設の用地は宅地ではない
A6: Q005 | B6: 宅地の定義 | C6: 駐車場として利用されている土地は宅地である | D6: ○ | E6: 建物敷地以外でも宅地に該当する場合がある
A7: Q006 | B7: 宅建業の定義 | C7: 宅地の売買を1回だけ行う場合宅建業に該当する | D7: × | E7: 宅建業は反復継続が必要
A8: Q007 | B8: 宅建業の定義 | C8: 宅地の売買を反復継続して行う場合宅建業となる | D8: ○ | E8: 反復継続して売買する場合は宅建業
A9: Q008 | B9: 宅建業の定義 | C9: 建物の賃貸の媒介は宅建業である | D9: ○ | E9: 賃貸の代理・媒介は宅建業
A10: Q009 | B10: 宅建業の定義 | C10: 自ら貸主として賃貸する行為は宅建業である | D10: × | E10: 貸借は宅建業に含まれない
A11: Q010 | B11: 宅建業の定義 | C11: 宅地売買の媒介は宅建業に該当する | D11: ○ | E11: 売買の媒介は宅建業
A13: Q011 | B13: 免許制度 | C13: 宅建業免許の有効期間は5年である | D13: ○ | E13: 宅建業免許は5年ごと更新
... A139: Q125 | B139: 罰則 | C139: 名義貸しは禁止されている | D139: ○ | E139: 宅建業者の名義貸しは禁止

Sheet 回答シート
A1: source_sheet | B1: question_no | C1: question | D1: answer | E1: question_image_path | F1: answer_image_path | G1: image_path | H1: explanation | I1: subject | J1: tags | K1: keywords | L1: mistakes | M1: consecutive_ok | N1: last_miss | O1: last_ok
A2: シート名 | B2: № | C2: 問題 | D2: 正解 | E2: タグ | F2: 検索キーワード | G2: タグ | H2: 検索キーワード | I2: 科目名 | J2: タグ | K2: 検索キーワード | L2: 間違い回数 | M2: 連続正解回数 | N2: 最終不正解日 | O2: 最終正解日
A3: 財務会計 | B3: 2 | C3: 財務諸表は？ | D3: B/S、P/L、株主資本等変動計画書、キャッシュフロー計算書、附属明細表 | F3: image/out_1080x1350/zaimu_q02.png | G3: image/out_1080x1350/zaimu_q02.png | I3: 第２章財務諸表概論 | L3: 1 | M3: 1 | N3: 2026-03-04 13:20:51 | O3: 2026-03-04 13:30:12
A4: 財務会計 | B4: 4 | C4: CF計算書の種類 | D4: 営業CF、投資CF、財務CF | I4: 第２章財務諸表概論 | L4: 1 | M4: 0 | N4: 2026-03-04 13:31:05
A5: 財務会計 | B5: 5 | C5: B/S、P/L、C/Fの経営分析における意義は？ | D5: 安全性、効率性、収益性 | I5: 第２章財務諸表概論 | L5: 0 | M5: 1 | O5: 2026-03-04 13:31:30
A6: 財務会計 | B6: 1.0 | C6: 計算書類は？ | D6: B/S、P/L、株主資本等変動計画書、個別注記表 | I6: 第２章財務諸表概論 | L6: 1 | M6: 0 | N6: 2026-03-06 17:34:41
